{
"type": "FeatureCollection",
"name": "geo_01_地域密着型特定施設入居者生活介護（軽費老人ホーム）",
"crs": { "type": "name", "properties": { "name": "urn:ogc:def:crs:OGC:1.3:CRS84" } },
"features": [
{ "type": "Feature", "properties": { "内容": "社会福祉法人母恋　ケアハウス絆【地域密着型特定施設入居者生活介護（軽費老人ホーム）】北海道室蘭市新富町1丁目2番32号ケアハウス絆", "url": "https://www.kaigokensaku.mhlw.go.jp/01/index.php?action_kouhyou_detail_004_kani=true&JigyosyoCd=0193500014-00&ServiceCd=362&Type=search", "url2": "https://www.shafukubokoi.net" }, "geometry": { "type": "Point", "coordinates": [ 140.988144649598667, 42.316380666765454 ] } },
{ "type": "Feature", "properties": { "内容": "ケアハウス白鳥の丘【地域密着型特定施設入居者生活介護（軽費老人ホーム）】室蘭市白鳥台５丁目１８番５号", "url": "https://www.kaigokensaku.mhlw.go.jp/01/index.php?action_kouhyou_detail_004_kani=true&JigyosyoCd=0193500048-00&ServiceCd=362&Type=search", "url2": "http://taiheiyo.jp/webpage/care-house.html" }, "geometry": { "type": "Point", "coordinates": [ 140.941959200000042, 42.3801451 ] } },
{ "type": "Feature", "properties": { "内容": "ケアハウスゆうあい【地域密着型特定施設入居者生活介護（軽費老人ホーム）】北海道北見市美芳町1丁目8番17号", "url": "https://www.kaigokensaku.mhlw.go.jp/01/index.php?action_kouhyou_detail_004_kani=true&JigyosyoCd=0195000021-00&ServiceCd=362&Type=search", "url2": "http://kitami-yuuaikai.or.jp/" }, "geometry": { "type": "Point", "coordinates": [ 143.880468800000017, 43.8082334 ] } },
{ "type": "Feature", "properties": { "内容": "ケアハウス森の灯りはまなす【地域密着型特定施設入居者生活介護（軽費老人ホーム）】網走市つくしヶ丘３丁目９－１", "url": "https://www.kaigokensaku.mhlw.go.jp/01/index.php?action_kouhyou_detail_004_kani=true&JigyosyoCd=0195300090-00&ServiceCd=362&Type=search", "url2": "https://morinoakarihamanasu.com/" }, "geometry": { "type": "Point", "coordinates": [ 144.279837600000064, 43.9930015 ] } },
{ "type": "Feature", "properties": { "内容": "地域密着型ケアハウスリバーサイド【地域密着型特定施設入居者生活介護（軽費老人ホーム）】北海道苫小牧市松風町2番15号", "url": "https://www.kaigokensaku.mhlw.go.jp/01/index.php?action_kouhyou_detail_004_kani=true&JigyosyoCd=0193600327-00&ServiceCd=362&Type=search", "url2": "http://www.ryokuyoukai.or.jp/" }, "geometry": { "type": "Point", "coordinates": [ 141.558639800000037, 42.6378276 ] } },
{ "type": "Feature", "properties": { "内容": "地域密着型特定施設入居者生活介護　ケアハウス風華【地域密着型特定施設入居者生活介護（軽費老人ホーム）】北海道名寄市風連町新生町１８２番１", "url": "https://www.kaigokensaku.mhlw.go.jp/01/index.php?action_kouhyou_detail_004_kani=true&JigyosyoCd=0193200227-00&ServiceCd=362&Type=search", "url2": "https://kousei-fukushikai.com" }, "geometry": { "type": "Point", "coordinates": [ 142.426575858999655, 44.295814702016258 ] } },
{ "type": "Feature", "properties": { "内容": "ケアハウスえんれい草【地域密着型特定施設入居者生活介護（軽費老人ホーム）】北海道深川市４条１２番６号", "url": "https://www.kaigokensaku.mhlw.go.jp/01/index.php?action_kouhyou_detail_004_kani=true&JigyosyoCd=0197400088-00&ServiceCd=362&Type=search", "url2": "http://www.henry-dunant.or.jp" }, "geometry": { "type": "Point", "coordinates": [ 142.04781700489346, 43.720286346437405 ] } },
{ "type": "Feature", "properties": { "内容": "ケアハウスかもめ荘【地域密着型特定施設入居者生活介護（軽費老人ホーム）】北海道檜山郡江差町字桧岱２１７番地３", "url": "https://www.kaigokensaku.mhlw.go.jp/01/index.php?action_kouhyou_detail_004_kani=true&JigyosyoCd=0191600022-00&ServiceCd=362&Type=search", "url2": "http://www.hinokikai.jp" }, "geometry": { "type": "Point", "coordinates": [ 140.146356100000048, 41.8690509 ] } }
]
}
